energy_consumption_reporter/.gitkeep
energy_consumption_reporter/__init__.py
energy_consumption_reporter/auto_detect.py
energy_consumption_reporter/data/cpu_power.csv
energy_consumption_reporter/data/spec_data_cleaned.csv
energy_consumption_reporter/energy_model.py
energy_consumption_reporter/energy_tester.py
energy_consumption_reporter/energyreport/.gitkeep
energy_consumption_reporter/measure_process.py
energy_consumption_reporter/report_builder.py
energy_consumption_reporter/singleton.py
energy_consumption_reporter-0.1.7.dist-info/LICENSE
energy_consumption_reporter-0.1.7.dist-info/METADATA
energy_consumption_reporter-0.1.7.dist-info/WHEEL
energy_consumption_reporter-0.1.7.dist-info/RECORD
