Metadata-Version: 2.1
Name: energy_consumption_reporter
Version: 0.1.7
Summary: An energy consumption measuring and reporting tool
License: LICENSE
Keywords: energy,consumption,reporter
Author: Rodin Haker
Author-email: rodinhaker@hotmail.com
Maintainer: Rodin Haker
Maintainer-email: rodinhaker@hotmail.com
Requires-Python: >=3.10,<4.0
Classifier: Development Status :: 3 - Alpha
Classifier: Framework :: Pytest
Classifier: Intended Audience :: Developers
Classifier: License :: Other/Proprietary License
Classifier: Programming Language :: Python
Classifier: Programming Language :: Python :: 3
Classifier: Programming Language :: Python :: 3.10
Classifier: Programming Language :: Python :: 3.11
Classifier: Programming Language :: Python :: 3.12
Requires-Dist: pandas (==2.2.0)
Requires-Dist: psutil (==5.9.8)
Requires-Dist: scikit-learn (>=1.4.1.post1,<2.0.0)
Requires-Dist: setuptools (>=69.2.0,<70.0.0)
Requires-Dist: wmi (==1.5.1) ; sys_platform == "win32"
Requires-Dist: xgboost (==2.0.3)
Project-URL: Bug Tracker, https://github.com/aron-hoogeveen/energy-consumption-reporter/issues
Project-URL: Documentation, https://github.com/aron-hoogeveen/energy-consumption-reporter
Project-URL: Homepage, https://github.com/aron-hoogeveen/energy-consumption-reporter
Project-URL: Repository, https://github.com/aron-hoogeveen/energy-consumption-reporter
